paxLibUL/__init__.py
paxLibUL/convolution/__init__.py
paxLibUL/convolution/architectures.py
paxLibUL/convolution/callbacks.py
paxLibUL/convolution/datasets.py
paxLibUL/convolution/visualisation.py
paxLibUL/convolution/weights_init.py
paxLibUL/nlp/__init__.py
paxLibUL/nlp/data_transformer.py
paxLibUL/nlp/datasets.py
paxLibUL/nlp/evaluate.py
paxlibul-0.2.1.dist-info/licenses/LICENSE
paxlibul-0.2.1.dist-info/METADATA
paxlibul-0.2.1.dist-info/WHEEL
paxlibul-0.2.1.dist-info/top_level.txt
paxlibul-0.2.1.dist-info/RECORD
